{
    "zh-CN": [
        {
            "name": "guide",
            "title": "开发指南",
            "path": "/index"
        },
        {
            "name": "log",
            "title": "更新日志",
            "path": "/changelog"
        },
        {
            "name": "i18n",
            "title": "国际化",
            "path": "/i18n"
        },
        {
            "title": "代码规范",
            "href": "https://github.com/fmfe/fe-coding-style-guide/"
        },
        {
            "title": "Table 组件",
            "href": "https://github.com/dwqs/v2-table"
        },
        {
            "title": "Datepicker 组件",
            "href": "https://github.com/dwqs/v2-datepicker"
        },
        {
            "title": "LazyList 组件",
            "href": "https://github.com/dwqs/v2-lazy-list"
        },
        {
            "title": "Scrollbar 组件",
            "href": "https://github.com/dwqs/beautify-scrollbar"
        },
        {
            "title": "基础组件",
            "children": [
                {
                    "title": "Utils 工具库",
                    "name": "util",
                    "path": "/utils"
                },
                {
                    "title": "Button 按钮",
                    "name": "button",
                    "path": "/button"
                },
                {
                    "title": "Dialog 对话框",
                    "name": "dialog",
                    "path": "/dialog"
                },
                {
                    "title": "Loading 加载",
                    "name": "loading",
                    "path": "/loading"
                },
                {
                    "title": "Collapse 折叠面板",
                    "name": "collapse",
                    "path": "/collapse"
                },
                {
                    "title": "Tabs 标签页",
                    "name": "tabs",
                    "path": "/tabs"
                },
                {
                    "title": "Rate 评分",
                    "name": "rate",
                    "path": "/rate"
                },
                {
                    "title": "Carousel 走马灯",
                    "name": "carousel",
                    "path": "/carousel"
                },
                {
                    "title": "Input 输入框",
                    "name": "input",
                    "path": "/input"
                },
                {
                    "title": "Checkbox 多选框",
                    "name": "checkbox",
                    "path": "/checkbox"
                },
                {
                    "title": "Radio 单选框",
                    "name": "radio",
                    "path": "/radio"
                },
                {
                    "title": "Switch 开关",
                    "name": "switch",
                    "path": "/switch"
                },
                {
                    "title": "Select 选择器",
                    "name": "select",
                    "path": "/select"
                },
                {
                    "title": "RBG 按钮组",
                    "name": "rbg",
                    "path": "/rbg"
                }
            ]
        }
    ]
}
